setup.cfg
setup.py
NFL_Draftkings/ConvertToDraftKings.py
NFL_Draftkings/GatherPlayerData.py
NFL_Draftkings/GetPlayerDKScores.py
NFL_Draftkings/GetPlayerStats.py
NFL_Draftkings/ProcessPlayerStats.py
NFL_Draftkings/__init__.py
NFL_Draftkings/constants.py
NFL_Draftkings/run.py
NFL_Draftkings.egg-info/PKG-INFO
NFL_Draftkings.egg-info/SOURCES.txt
NFL_Draftkings.egg-info/dependency_links.txt
NFL_Draftkings.egg-info/top_level.txt