Metadata-Version: 1.1
Name: NFL-Draftkings
Version: 2
Summary: Python wrapper around NFL api that calculates Draftkings scores for players
Home-page: https://github.com/kacperadach/NFL_Draftkings
Author: Kacper Adach
Author-email: kacperadach@gmail.com
License: UNKNOWN
Download-URL: https://github.com/kacperadach/NFL_Draftkings/tarball/2
Keywords: nfl,draftkings,python,api,wrapper,player,scores,points
Platform: UNKNOWN
